nbtop/__init__.py
nbtop/main.py
nbtop/version.py
nbtop-0.5.0.dist-info/DESCRIPTION.rst
nbtop-0.5.0.dist-info/METADATA
nbtop-0.5.0.dist-info/RECORD
nbtop-0.5.0.dist-info/WHEEL
nbtop-0.5.0.dist-info/entry_points.txt
nbtop-0.5.0.dist-info/metadata.json
nbtop-0.5.0.dist-info/top_level.txt
