Metadata-Version: 2.0
Name: nbtop
Version: 0.5.0
Summary: resource monitor for IPython Notebook servers
Home-page: https://github.com/iiSeymour/nbtop
Author: Chris Seymour
Author-email: chris.j.seymour@hotmail.com
License: MIT
Platform: UNKNOWN
Requires-Dist: psutil (>=2.2.1)
Requires-Dist: requests (>=2.7.0)
Requires-Dist: simplejson (>=3.3.1)
Requires-Dist: six (>=1.9.0)
